[
  {"la_code":873,"est_name":"The Starship Children's Centre","est_type_code":47,"phase_code":0},
  {"la_code":380,"est_name":"Abbey Green Nursery School & Children's Centre","est_type_code":47,"phase_code":0},
  {"la_code":806,"est_name":"Abingdon Children's Centre","est_type_code":47,"phase_code":0},
  {"la_code":928,"est_name":"Abington Library and Children's Centre","est_type_code":47,"phase_code":0},
  {"la_code":340,"est_name":"Stockbridge Village (Acorn) SSCC","est_type_code":47,"phase_code":0},
  {"la_code":935,"est_name":"Acorns Children's Centre","est_type_code":47,"phase_code":0},
  {"la_code":928,"est_name":"Montagu Street Children's Centre","est_type_code":47,"phase_code":0},
  {"la_code":371,"est_name":"Adwick Children's Centre","est_type_code":47,"phase_code":0},
  {"la_code":867,"est_name":"Alders and Chestnuts Children's Centre","est_type_code":47,"phase_code":0},
  {"la_code":353,"est_name":"Alexandra Children's Centre","est_type_code":47,"phase_code":0}
]
